pycolorgenerator/__init__.py
pycolorgenerator-1.0.2.dist-info/LICENSE
pycolorgenerator-1.0.2.dist-info/METADATA
pycolorgenerator-1.0.2.dist-info/WHEEL
pycolorgenerator-1.0.2.dist-info/top_level.txt
pycolorgenerator-1.0.2.dist-info/RECORD
