Metadata-Version: 2.1
Name: pycolorgenerator
Version: 1.0.2
Summary: A package for simple different colors generation
Home-page: https://github.com/Chebotarev-Alexey/pycolorgenerator
Author: Alexey-Chebotarev
Classifier: Programming Language :: Python :: 3
Classifier: License :: OSI Approved :: MIT License
Classifier: Operating System :: OS Independent
Requires-Python: >=3.6
License-File: LICENSE
